MANIFEST.in
README.md
VERSION
setup.py
ra/__init__.py
ra/dsl.py
ra/factory.py
ra/marks.py
ra/raml.py
ra/request.py
ra/utils.py
ra/validate.py
ra.egg-info/PKG-INFO
ra.egg-info/SOURCES.txt
ra.egg-info/dependency_links.txt
ra.egg-info/entry_points.txt
ra.egg-info/not-zip-safe
ra.egg-info/requires.txt
ra.egg-info/top_level.txt
ra/plugins/__init__.py
ra/plugins/pytest_.py