Metadata-Version: 1.1
Name: ra
Version: 0.1.1
Summary: Test RAML API definition
Home-page: https://github.com/ramses-tech/ra
Author: Ramses
Author-email: hello@ramses.tech
License: UNKNOWN
Keywords: web raml
Platform: UNKNOWN
Classifier: Programming Language :: Python
Classifier: Programming Language :: Python :: 2
Classifier: Programming Language :: Python :: 2.7
Classifier: Programming Language :: Python :: 3
Classifier: Programming Language :: Python :: 3.4
Classifier: Framework :: Pyramid
Classifier: Topic :: Internet :: WWW/HTTP
Classifier: Topic :: Internet :: WWW/HTTP :: WSGI :: Application
